{
    "type": "Collection",
    "id": "ASA_AP__0P_Scenes_NA",
    "stac_version": "1.0.0",
    "description": "The ASAR Alternating Polarization Mode Level 0 (Co-polar and Cross-polar H and V) products contain time-ordered Annotated Instrument Source Packets (AISPs) corresponding to one of the three possible polarisation combinations: HH & HV, VV & VH and HH & VV, respectively.   The echo samples in the AISPs have been compressed to 4 bits/sample using FBAQ.  This is a high-rate, narrow swath mode, so data is only acquired for partial orbit segments. There are two co-registered images per acquisition and may be from one of seven different image swaths.   The Level 0 product was produced systematically for all data acquired within this mode. Data Size: 56-100 km across track x 100 km along track  There are three AP Mode Level 0 products:   - ASA_APH_0P:  The Cross-polar H Level 0 product corresponds to the polarisation combination HH/HV.  - ASA_APV_0P: The Cross-polar V Level 0 product corresponds to the polarisation combination VV/VH.   - ASA_APC_0P:  The Co-polar Level 0 product corresponds to the polarisation combination HH/VV= H and H received/V transmit and V received.",
    "links": [
        {
            "rel": "license",
            "href": "https://science.nasa.gov/earth-science/earth-science-data/data-information-policy",
            "type": "text/html",
            "title": "EOSDIS Data Use Policy"
        },
        {
            "rel": "about",
            "href": "https://cmr.earthdata.nasa.gov/search/concepts/C1965336818-ESA.html",
            "type": "text/html",
            "title": "HTML metadata for collection"
        },
        {
            "rel": "via",
            "href": "https://cmr.earthdata.nasa.gov/search/concepts/C1965336818-ESA.native",
            "type": "application/xml",
            "title": "Native metadata for collection"
        },
        {
            "rel": "via",
            "href": "https://cmr.earthdata.nasa.gov/search/concepts/C1965336818-ESA.echo10",
            "type": "application/echo10+xml",
            "title": "ECHO10 metadata for collection"
        },
        {
            "rel": "via",
            "href": "https://cmr.earthdata.nasa.gov/search/concepts/C1965336818-ESA.json",
            "type": "application/json",
            "title": "CMR JSON metadata for collection"
        },
        {
            "rel": "via",
            "href": "https://cmr.earthdata.nasa.gov/search/concepts/C1965336818-ESA.umm_json",
            "type": "application/vnd.nasa.cmr.umm+json",
            "title": "CMR UMM_JSON metadata for collection"
        },
        {
            "rel": "self",
            "href": "https://cmr.earthdata.nasa.gov/stac/ESA/collections/ASA_AP__0P_Scenes_NA",
            "type": "application/json"
        },
        {
            "rel": "root",
            "href": "https://cmr.earthdata.nasa.gov/stac/ESA",
            "type": "application/json",
            "title": "ESA STAC Catalog"
        },
        {
            "rel": "items",
            "href": "https://cmr.earthdata.nasa.gov/stac/ESA/collections/ASA_AP__0P_Scenes_NA/items",
            "type": "application/json"
        }
    ],
    "provider": [
        {
            "name": "ESA",
            "roles": [
                "producer"
            ]
        },
        {
            "name": "NASA EOSDIS",
            "roles": [
                "host"
            ]
        }
    ],
    "title": "Envisat ASAR AP Co- and Cross-polar L0 [ASA_APC/APH/APV_0P]",
    "extent": {
        "spatial": {
            "bbox": [
                [
                    -180,
                    -90,
                    180,
                    90
                ]
            ]
        },
        "temporal": {
            "interval": [
                [
                    "2002-11-15T00:00:00Z",
                    "2012-04-08T23:59:59.999000Z"
                ]
            ]
        }
    },
    "license": "proprietary",
    "keywords": [
        "EARTH SCIENCE",
        "AGRICULTURE",
        "SOILS",
        "BIOSPHERE",
        "VEGETATION",
        "CRYOSPHERE",
        "SNOW/ICE",
        "HUMAN DIMENSIONS",
        "NATURAL HAZARDS",
        "OCEANS",
        "OCEAN WAVES",
        "MARINE ENVIRONMENT MONITORING",
        "MARINE OBSTRUCTIONS"
    ],
    "summaries": {
        "platform": [
            "ENVISAT"
        ],
        "instruments": [
            "ASAR"
        ]
    },
    "assets": {
        "ceos": {
            "href": "https://fedeo-client.ceos.org?parentIdentifier=EOP:ESA:EARTH-ONLINE&uid=ASA_AP__0P_Scenes",
            "title": "Direct Download [0]",
            "description": "DescribedBy",
            "roles": [
                "data"
            ]
        },
        "iso": {
            "href": "https://fedeo.ceos.org/opensearch/request/?httpAccept=application/vnd.iso.19139-2%2Bxml&parentIdentifier=EOP:ESA:EARTH-ONLINE&uid=ASA_AP__0P_Scenes&recordSchema=iso19139-2",
            "title": "Direct Download [1]",
            "description": "DescribedBy",
            "roles": [
                "data"
            ]
        },
        "provider_metadata": {
            "href": "https://doi.org/10.5270/EN1-u55aesn",
            "title": "Provider Metadata",
            "description": "Landing Page",
            "roles": [
                "metadata"
            ]
        },
        "metadata": {
            "href": "https://cmr.earthdata.nasa.gov/search/concepts/C1965336818-ESA.xml",
            "type": "application/xml",
            "title": "CMR XML metadata for C1965336818-ESA",
            "roles": [
                "metadata"
            ]
        }
    }
}