{
    "type": "Collection",
    "id": "CWIC_REG_1.0",
    "stac_version": "1.0.0",
    "description": "The collection represents browse images and metadata for systematically georeferenced Radarsat-2 Synthetic Aperture Radar(SAR) satellite scenes. The browse scenes are not geometrically enhanced using ground control points, but are systematically corrected using sensor parameters. Full resolution precision geocoded scenes(corrected using ground control points) which correspond to the browse images can be ordered from MacDonald Dettwiler and Associates Ltd., Vancouver, Canada. Metadata discovery is achieved using the online catalog http://neodf.nrcan.gc.ca OR by using the CWIC OGC CSW service URL : http://cwic.csiss.gmu.edu/cwicv1/discovery. The imaging frequency is C Band SAR : 5405.0000 MHz. RADARSAT-2 is in a polar, sun-synchronous orbit with a period of approximately 101 minutes. The RADARSAT-2 orbit\nwill be maintained at +\\/- 1 km in across track direction. This orbit maintenance is suitable for InSAR data collection. The geo-location accuracy of RADARSAT-2 products varies with product type. It is currently estimated at +\\/- 30 m for Standard beam products.  The revisit period for RADARSAT-2 depends on the beam mode, incidence angle and geographic location of\nthe area of interest. In general, revisit is more frequent at the poles than the equator and the wider swath modes have higher revisit than t\nhe narrow swath modes.",
    "links": [
        {
            "rel": "license",
            "href": "https://science.nasa.gov/earth-science/earth-science-data/data-information-policy",
            "type": "text/html",
            "title": "EOSDIS Data Use Policy"
        },
        {
            "rel": "about",
            "href": "https://cmr.earthdata.nasa.gov/search/concepts/C2204659831-CCMEO.html",
            "type": "text/html",
            "title": "HTML metadata for collection"
        },
        {
            "rel": "via",
            "href": "https://cmr.earthdata.nasa.gov/search/concepts/C2204659831-CCMEO.native",
            "type": "application/xml",
            "title": "Native metadata for collection"
        },
        {
            "rel": "via",
            "href": "https://cmr.earthdata.nasa.gov/search/concepts/C2204659831-CCMEO.echo10",
            "type": "application/echo10+xml",
            "title": "ECHO10 metadata for collection"
        },
        {
            "rel": "via",
            "href": "https://cmr.earthdata.nasa.gov/search/concepts/C2204659831-CCMEO.json",
            "type": "application/json",
            "title": "CMR JSON metadata for collection"
        },
        {
            "rel": "via",
            "href": "https://cmr.earthdata.nasa.gov/search/concepts/C2204659831-CCMEO.umm_json",
            "type": "application/vnd.nasa.cmr.umm+json",
            "title": "CMR UMM_JSON metadata for collection"
        },
        {
            "rel": "self",
            "href": "https://cmr.earthdata.nasa.gov/stac/CCMEO/collections/CWIC_REG_1.0",
            "type": "application/json"
        },
        {
            "rel": "root",
            "href": "https://cmr.earthdata.nasa.gov/stac/CCMEO",
            "type": "application/json",
            "title": "CCMEO STAC Catalog"
        },
        {
            "rel": "items",
            "href": "https://cmr.earthdata.nasa.gov/stac/CCMEO/collections/CWIC_REG_1.0/items",
            "type": "application/json"
        }
    ],
    "provider": [
        {
            "name": "CCMEO",
            "roles": [
                "producer"
            ]
        },
        {
            "name": "NASA EOSDIS",
            "roles": [
                "host"
            ]
        }
    ],
    "title": "Radarsat-2 Scenes, Natural Resources Canada",
    "extent": {
        "spatial": {
            "bbox": [
                [
                    -180,
                    -90,
                    180,
                    90
                ]
            ]
        },
        "temporal": {
            "interval": [
                [
                    "2008-04-27T00:00:00Z",
                    null
                ]
            ]
        }
    },
    "license": "proprietary",
    "keywords": [
        "EARTH SCIENCE",
        "AGRICULTURE",
        "AGRICULTURAL PLANT SCIENCE",
        "CROP/PLANT YIELDS",
        "CROPPING SYSTEMS",
        "IRRIGATION",
        "FOREST SCIENCE",
        "FOREST CONSERVATION",
        "FOREST MANAGEMENT",
        "PLANT COMMODITIES",
        "FIELD CROP PRODUCTS",
        "OCEANS",
        "SEA ICE",
        "LAND SURFACE",
        "EROSION/SEDIMENTATION",
        "DEGRADATION",
        "EROSION",
        "LANDSLIDES",
        "SOILS",
        "SOIL MOISTURE/WATER CONTENT",
        "GEOMORPHIC LANDFORMS/PROCESSES",
        "TOPOGRAPHY",
        "TERRAIN ELEVATION",
        "TOPOGRAPHIC EFFECTS"
    ],
    "summaries": {
        "platform": [
            "RADARSAT-2"
        ],
        "instruments": [
            "C-SAR"
        ]
    },
    "assets": {
        "metadata": {
            "href": "https://cmr.earthdata.nasa.gov/search/concepts/C2204659831-CCMEO.xml",
            "type": "application/xml",
            "title": "CMR XML metadata for C2204659831-CCMEO",
            "roles": [
                "metadata"
            ]
        }
    }
}