{
    "type": "Collection",
    "id": "EO:EUM:CM:METOP:ASCSZFR02.v2014-10-07",
    "stac_version": "1.0.0",
    "description": "Reprocessed L1B data from the Advanced Scatterometer (ASCAT) on METOP-A, resampled at full resolution (SZF). Normalized radar cross section (NRCS) of the Earth surface together with measurement time, location (latitude and longitude) and geometrical information (incidence and azimuth angles). The prime objective of the Advanced SCATterometer (ASCAT) is to measure wind speed and direction over the oceans, and the main operational application is the assimilation of ocean winds in NWP models. Other operational applications, based on the use of measurements of the backscattering coefficient, are sea ice edge detection and monitoring, monitoring sea ice, snow cover, soil moisture and surface parameters. This product is also available at 12.5 and 25 km Swath Grids. This is a Fundamental Climate Data Record (FCDR). ",
    "links": [
        {
            "rel": "root",
            "href": "https://cmr.earthdata.nasa.gov/stac/",
            "type": "application/json",
            "title": "NASA CMR STAC Proxy"
        },
        {
            "rel": "items",
            "href": "https://cmr.earthdata.nasa.gov/stac/EUMETSAT/collections/EO:EUM:CM:METOP:ASCSZFR02.v2014-10-07/items",
            "type": "application/json",
            "title": "Granules in this collection"
        },
        {
            "rel": "about",
            "href": "https://cmr.earthdata.nasa.gov/search/concepts/C1588901388-EUMETSAT.html",
            "type": "text/html",
            "title": "HTML metadata for collection"
        },
        {
            "rel": "via",
            "href": "https://cmr.earthdata.nasa.gov/search/concepts/C1588901388-EUMETSAT.json",
            "type": "application/json",
            "title": "CMR JSON metadata for collection"
        },
        {
            "rel": "self",
            "href": "https://cmr.earthdata.nasa.gov/stac/EUMETSAT/collections/EO:EUM:CM:METOP:ASCSZFR02.v2014-10-07",
            "type": "application/json"
        },
        {
            "rel": "parent",
            "href": "https://cmr.earthdata.nasa.gov/stac/EUMETSAT",
            "type": "application/json",
            "title": "EUMETSAT"
        }
    ],
    "stac_extensions": [],
    "title": "ASCAT L1 SZF Climate Data Record Release 2 - Metop",
    "extent": {
        "spatial": {
            "bbox": [
                [
                    -180,
                    -90,
                    180,
                    90
                ]
            ]
        },
        "temporal": {
            "interval": [
                [
                    "2007-01-01T00:00:00Z",
                    "2014-03-31T23:59:59.999000Z"
                ]
            ]
        }
    },
    "license": "not-provided"
}