{
    "type": "Collection",
    "id": "OMG_L2_Bathy_MBES_Gridded_1",
    "stac_version": "1.0.0",
    "description": "This dataset contains level 2 in situ depth measurements from Multibeam Echo Sounder System (MBES) instruments. These depths were used to map the bathymetry around ocean terminating glaciers of Greenland. The bathymetry mapping is part of the Oceans Melting Greenland (OMG) project. The goal of the project is to find out what contributions the ocean has on Greenland's melting glaciers. The MBES was onboard a ship so the tracks are not of a swath, but less regularly patterned as the ship is limited as to where it can traverse due to floating glaciers, ice cover and general weather conditions. Bathymetry was also measured with the Singlebeam Echo Sounder System (SBES) in areas where the MBES could not go, but has less spatial coverage.",
    "links": [
        {
            "rel": "license",
            "href": "https://science.nasa.gov/earth-science/earth-science-data/data-information-policy",
            "type": "text/html",
            "title": "EOSDIS Data Use Policy"
        },
        {
            "rel": "about",
            "href": "https://cmr.earthdata.nasa.gov/search/concepts/C2491772154-POCLOUD.html",
            "type": "text/html",
            "title": "HTML metadata for collection"
        },
        {
            "rel": "via",
            "href": "https://cmr.earthdata.nasa.gov/search/concepts/C2491772154-POCLOUD.native",
            "type": "application/xml",
            "title": "Native metadata for collection"
        },
        {
            "rel": "via",
            "href": "https://cmr.earthdata.nasa.gov/search/concepts/C2491772154-POCLOUD.echo10",
            "type": "application/echo10+xml",
            "title": "ECHO10 metadata for collection"
        },
        {
            "rel": "via",
            "href": "https://cmr.earthdata.nasa.gov/search/concepts/C2491772154-POCLOUD.json",
            "type": "application/json",
            "title": "CMR JSON metadata for collection"
        },
        {
            "rel": "via",
            "href": "https://cmr.earthdata.nasa.gov/search/concepts/C2491772154-POCLOUD.umm_json",
            "type": "application/vnd.nasa.cmr.umm+json",
            "title": "CMR UMM_JSON metadata for collection"
        },
        {
            "rel": "self",
            "href": "https://cmr.earthdata.nasa.gov/stac/POCLOUD/collections/OMG_L2_Bathy_MBES_Gridded_1",
            "type": "application/json"
        },
        {
            "rel": "root",
            "href": "https://cmr.earthdata.nasa.gov/stac/POCLOUD",
            "type": "application/json",
            "title": "POCLOUD STAC Catalog"
        },
        {
            "rel": "items",
            "href": "https://cmr.earthdata.nasa.gov/stac/POCLOUD/collections/OMG_L2_Bathy_MBES_Gridded_1/items",
            "type": "application/json"
        }
    ],
    "provider": [
        {
            "name": "POCLOUD",
            "roles": [
                "producer"
            ]
        },
        {
            "name": "NASA EOSDIS",
            "roles": [
                "host"
            ]
        }
    ],
    "title": "OMG Swath Gridded Multibeam Echo Sounding (MBES) Bathymetry",
    "extent": {
        "spatial": {
            "bbox": [
                [
                    -73.6,
                    59.1,
                    -6.9,
                    83.6
                ]
            ]
        },
        "temporal": {
            "interval": [
                [
                    "2015-07-25T00:00:00Z",
                    "2021-08-31T23:59:59.999000Z"
                ]
            ]
        }
    },
    "license": "proprietary",
    "keywords": [
        "EARTH SCIENCE",
        "BATHYMETRY",
        "BATHYMETRY/SEAFLOOR TOPOGRAPHY",
        "OCEANS"
    ],
    "summaries": {
        "platform": [
            "OMGSHIP_MBES"
        ],
        "instruments": [
            "MBES"
        ]
    },
    "assets": {
        "browse": {
            "href": "https://podaac.jpl.nasa.gov/Podaac/thumbnails/OMG_L2_Bathy_MBES_Gridded.jpg",
            "type": "image/jpeg",
            "title": "Download OMG_L2_Bathy_MBES_Gridded.jpg",
            "roles": [
                "browse"
            ]
        },
        "thumbnail": {
            "href": "https://podaac.jpl.nasa.gov/Podaac/thumbnails/OMG_L2_Bathy_MBES_Gridded.jpg",
            "title": "Thumbnail",
            "description": "Thumbnail",
            "roles": [
                "thumbnail"
            ]
        },
        "nasa": {
            "href": "https://search.earthdata.nasa.gov/search/granules?p=C2491772154-POCLOUD",
            "title": "Direct Download [1]",
            "description": "Browse granule search results in Earthdata Search",
            "roles": [
                "data"
            ]
        },
        "s3_podaac_ops_cumulus_protected_OMG_L2_Bathy_MBES_Gridded_": {
            "href": "s3://podaac-ops-cumulus-protected/OMG_L2_Bathy_MBES_Gridded/",
            "title": "podaac_ops_cumulus_protected_OMG_L2_Bathy_MBES_Gridded_",
            "roles": [
                "data"
            ]
        },
        "s3_podaac_ops_cumulus_public_OMG_L2_Bathy_MBES_Gridded_": {
            "href": "s3://podaac-ops-cumulus-public/OMG_L2_Bathy_MBES_Gridded/",
            "title": "podaac_ops_cumulus_public_OMG_L2_Bathy_MBES_Gridded_",
            "roles": [
                "data"
            ]
        },
        "s3_credentials": {
            "href": "https://archive.podaac.earthdata.nasa.gov/s3credentials",
            "title": "S3 credentials API endpoint",
            "roles": [
                "metadata"
            ]
        },
        "s3_credentials_documentation": {
            "href": "https://archive.podaac.earthdata.nasa.gov/s3credentialsREADME",
            "title": "S3 credentials API endpoint documentation",
            "roles": [
                "metadata"
            ]
        },
        "metadata": {
            "href": "https://cmr.earthdata.nasa.gov/search/concepts/C2491772154-POCLOUD.xml",
            "type": "application/xml",
            "title": "CMR XML metadata for C2491772154-POCLOUD",
            "roles": [
                "metadata"
            ]
        }
    }
}