{
    "type": "Collection",
    "id": "SBUVN07L2_1",
    "stac_version": "1.0.0",
    "description": "The Solar Backscattered Ultraviolet (SBUV) from Nimbus-7 Level-2 daily product (SBUVN07L2) contains ozone nadir profile and total column data from retrievals generated from the v8.6 SBUV algorithm. The v8.6 SBUV algorithm estimates the ozone nadir profile and total column from SBUV measurements using 1) the Brion-Daumont-Malicet ozone cross sections, 2) an OMI-derived cloud-height climatology, 3) a revised a priori ozone climatology, and 4) inter-instrument calibration based on comparisons with no local time difference.\n\nThe SBUVN07L2 product is written as daily files using the HDF5 format, with file sizes ranging from about 1 to 5 Mbytes. Data are available from November 1978 through May 1990. The SBUVN07L2 data product was used as input in creating the SBUVN07L3zm monthly zonal mean data product.",
    "links": [
        {
            "rel": "license",
            "href": "https://science.nasa.gov/earth-science/earth-science-data/data-information-policy",
            "type": "text/html",
            "title": "EOSDIS Data Use Policy"
        },
        {
            "rel": "about",
            "href": "https://cmr.earthdata.nasa.gov/search/concepts/C1251051726-GES_DISC.html",
            "type": "text/html",
            "title": "HTML metadata for collection"
        },
        {
            "rel": "via",
            "href": "https://cmr.earthdata.nasa.gov/search/concepts/C1251051726-GES_DISC.native",
            "type": "application/xml",
            "title": "Native metadata for collection"
        },
        {
            "rel": "via",
            "href": "https://cmr.earthdata.nasa.gov/search/concepts/C1251051726-GES_DISC.echo10",
            "type": "application/echo10+xml",
            "title": "ECHO10 metadata for collection"
        },
        {
            "rel": "via",
            "href": "https://cmr.earthdata.nasa.gov/search/concepts/C1251051726-GES_DISC.json",
            "type": "application/json",
            "title": "CMR JSON metadata for collection"
        },
        {
            "rel": "via",
            "href": "https://cmr.earthdata.nasa.gov/search/concepts/C1251051726-GES_DISC.umm_json",
            "type": "application/vnd.nasa.cmr.umm+json",
            "title": "CMR UMM_JSON metadata for collection"
        },
        {
            "rel": "self",
            "href": "https://cmr.earthdata.nasa.gov/stac/GES_DISC/collections/SBUVN07L2_1",
            "type": "application/json"
        },
        {
            "rel": "root",
            "href": "https://cmr.earthdata.nasa.gov/stac/GES_DISC",
            "type": "application/json",
            "title": "GES_DISC STAC Catalog"
        },
        {
            "rel": "items",
            "href": "https://cmr.earthdata.nasa.gov/stac/GES_DISC/collections/SBUVN07L2_1/items",
            "type": "application/json"
        }
    ],
    "provider": [
        {
            "name": "GES_DISC",
            "roles": [
                "producer"
            ]
        },
        {
            "name": "NASA EOSDIS",
            "roles": [
                "host"
            ]
        }
    ],
    "title": "SBUV/Nimbus-7 Ozone (O3) Nadir Profile and Total Column 1 Day L2 V1 (SBUVN07L2) at GES DISC",
    "extent": {
        "spatial": {
            "bbox": [
                [
                    -180,
                    -90,
                    180,
                    90
                ]
            ]
        },
        "temporal": {
            "interval": [
                [
                    "1978-10-31T00:00:00Z",
                    "1990-06-21T23:59:59.999000Z"
                ]
            ]
        }
    },
    "license": "proprietary",
    "keywords": [
        "EARTH SCIENCE",
        "ATMOSPHERE",
        "ATMOSPHERIC CHEMISTRY",
        "OXYGEN COMPOUNDS",
        "ATMOSPHERIC OZONE"
    ],
    "summaries": {
        "platform": [
            "Nimbus-7"
        ],
        "instruments": [
            "SBUV"
        ]
    },
    "assets": {
        "browse": {
            "href": "https://docserver.gesdisc.eosdis.nasa.gov/public/project/Images/SBUVN07L2_1.png",
            "type": "image/jpeg",
            "title": "Download SBUVN07L2_1.png",
            "roles": [
                "browse"
            ]
        },
        "thumbnail": {
            "href": "https://docserver.gesdisc.eosdis.nasa.gov/public/project/Images/SBUVN07L2_1.png",
            "title": "Thumbnail",
            "roles": [
                "thumbnail"
            ]
        },
        "gov/data/Ozone/SBUVN07L2": {
            "href": "https://measures.gesdisc.eosdis.nasa.gov/data/Ozone/SBUVN07L2.1/",
            "title": "Direct Download",
            "description": "Access the data via HTTP.",
            "roles": [
                "data"
            ]
        },
        "provider_metadata": {
            "href": "https://disc.gsfc.nasa.gov/datacollection/SBUVN07L2_1.html",
            "title": "Provider Metadata",
            "description": "Access the dataset landing page from the GES DISC website.",
            "roles": [
                "metadata"
            ]
        },
        "metadata": {
            "href": "https://cmr.earthdata.nasa.gov/search/concepts/C1251051726-GES_DISC.xml",
            "type": "application/xml",
            "title": "CMR XML metadata for C1251051726-GES_DISC",
            "roles": [
                "metadata"
            ]
        }
    }
}