{
    "type": "Collection",
    "id": "SNEX20_COCP_SPD_1",
    "stac_version": "1.0.0",
    "description": "This data set contains the results of ground-penetrating radar surveys conducted at Cameron Pass, Colorado during the SnowEx20 campaign. Data include two-way travel time, lidar-measured snow depth, derived snow water equivalent, derived snow density, and derived relative permittivity. Ground-penetrating radar two-way travel times were sourced from two previously published data sets: <a href=\"https://doi.org/10.5067/U4Q3X27BMRR4\">SnowEx20 Cameron Pass Ground Penetrating Radar, Version 1</a> and <a href=\"https://doi.org/10.5067/SRWGLYCB6ZC4\">SnowEx21 Cameron Pass Ground Penetrating Radar, Version 1</a>. The new data presented here represents a recalculation of the snow water equivalent (SWE), snow density, and relative permittivity using terrestrial lidar scan (TLS) data.",
    "links": [
        {
            "rel": "license",
            "href": "https://science.nasa.gov/earth-science/earth-science-data/data-information-policy",
            "type": "text/html",
            "title": "EOSDIS Data Use Policy"
        },
        {
            "rel": "about",
            "href": "https://cmr.earthdata.nasa.gov/search/concepts/C2888869172-NSIDC_ECS.html",
            "type": "text/html",
            "title": "HTML metadata for collection"
        },
        {
            "rel": "via",
            "href": "https://cmr.earthdata.nasa.gov/search/concepts/C2888869172-NSIDC_ECS.native",
            "type": "application/xml",
            "title": "Native metadata for collection"
        },
        {
            "rel": "via",
            "href": "https://cmr.earthdata.nasa.gov/search/concepts/C2888869172-NSIDC_ECS.echo10",
            "type": "application/echo10+xml",
            "title": "ECHO10 metadata for collection"
        },
        {
            "rel": "via",
            "href": "https://cmr.earthdata.nasa.gov/search/concepts/C2888869172-NSIDC_ECS.json",
            "type": "application/json",
            "title": "CMR JSON metadata for collection"
        },
        {
            "rel": "via",
            "href": "https://cmr.earthdata.nasa.gov/search/concepts/C2888869172-NSIDC_ECS.umm_json",
            "type": "application/vnd.nasa.cmr.umm+json",
            "title": "CMR UMM_JSON metadata for collection"
        },
        {
            "rel": "self",
            "href": "https://cmr.earthdata.nasa.gov/stac/NSIDC_ECS/collections/SNEX20_COCP_SPD_1",
            "type": "application/json"
        },
        {
            "rel": "root",
            "href": "https://cmr.earthdata.nasa.gov/stac/NSIDC_ECS",
            "type": "application/json",
            "title": "NSIDC_ECS STAC Catalog"
        },
        {
            "rel": "items",
            "href": "https://cmr.earthdata.nasa.gov/stac/NSIDC_ECS/collections/SNEX20_COCP_SPD_1/items",
            "type": "application/geo+json",
            "title": "Collection Items"
        }
    ],
    "provider": [
        {
            "name": "NSIDC_ECS",
            "roles": [
                "producer"
            ]
        },
        {
            "name": "NASA EOSDIS",
            "roles": [
                "host"
            ]
        }
    ],
    "title": "SnowEx20-21 Cameron Pass Derived Snowpack Relative Permittivities and Densities from Ground Penetrating Radar V001",
    "extent": {
        "spatial": {
            "bbox": [
                [
                    -105.8931,
                    40.5154,
                    -105.8889,
                    40.5202
                ]
            ]
        },
        "temporal": {
            "interval": [
                [
                    "2019-12-18T00:00:00Z",
                    "2021-05-27T23:59:59.999000Z"
                ]
            ]
        }
    },
    "license": "proprietary",
    "keywords": [
        "EARTH SCIENCE",
        "CRYOSPHERE",
        "SNOW/ICE",
        "SNOW DENSITY",
        "SNOW DEPTH",
        "SNOW WATER EQUIVALENT",
        "SPECTRAL/ENGINEERING",
        "RADAR",
        "RADAR REFLECTIVITY",
        "Two-Way Travel Time"
    ],
    "summaries": {
        "platform": [
            "GROUND-BASED OBSERVATIONS"
        ],
        "instruments": [
            "GPR",
            "LIDAR"
        ]
    },
    "assets": {
        "org/SNOWEX/SNEX20_COCP_SPD": {
            "href": "https://n5eil01u.ecs.nsidc.org/SNOWEX/SNEX20_COCP_SPD.001/",
            "title": "Direct Download [0]",
            "description": "Direct download via HTTPS protocol.",
            "roles": [
                "data"
            ]
        },
        "nasa": {
            "href": "https://search.earthdata.nasa.gov/search?q=SNEX20_COCP_SPD+V001",
            "title": "Direct Download [1]",
            "description": "NASA's newest search and order tool for subsetting, reprojecting, and reformatting data.",
            "roles": [
                "data"
            ]
        },
        "https://nsidc": {
            "href": "https://nsidc.org/data/data-access-tool/SNEX20_COCP_SPD/versions/1/",
            "title": "Direct Download [2]",
            "description": "Search and filter data files using a map-based interface",
            "roles": [
                "data"
            ]
        },
        "provider_metadata": {
            "href": "https://doi.org/10.5067/W0EJNWUZBYSL",
            "title": "Provider Metadata",
            "description": "Provides access to data, documentation, tools, citation information, support, and other resources.",
            "roles": [
                "metadata"
            ]
        },
        "metadata": {
            "href": "https://cmr.earthdata.nasa.gov/search/concepts/C2888869172-NSIDC_ECS.xml",
            "type": "application/xml",
            "title": "CMR XML metadata for C2888869172-NSIDC_ECS",
            "roles": [
                "metadata"
            ]
        }
    }
}